{
  "type": "minecraft:crafting_shaped",
  "pattern": [
    "XZX",
    "YBY",
    "ACA"
  ],
  "key": {
    "X": {
      "item": "minecraft:black_dye"
    },
    "Y": {
      "item": "minecraft:yellow_dye"
    },
    "Z": {
      "item": "enhanced_quarries:normal_marker"
    },
    "A": {
      "item": "enhanced_quarries:refined_gear"
    },
    "B": {
      "item": "minecraft:chest"
    },
    "C": {
      "item": "minecraft:crafting_table"
    }
  },
  "result": {
    "item": "enhanced_quarries:normal_filler",
    "id": "enhanced_quarries:normal_filler",
    "count": 1
  }
}